relint/__init__.py
relint/__main__.py
relint/_version.py
relint/config.py
relint/exceptions.py
relint/parse.py
relint-3.3.1.dist-info/entry_points.txt
relint-3.3.1.dist-info/LICENSE
relint-3.3.1.dist-info/WHEEL
relint-3.3.1.dist-info/METADATA
relint-3.3.1.dist-info/RECORD
