Metadata-Version: 2.1
Name: relint
Version: 3.3.1
Summary: Write your own linting rules using regular expressions.
Keywords: regex,linter
Author-email: Johannes Maron <johannes@maron.family>
Requires-Python: >=3.8
Classifier: Development Status :: 5 - Production/Stable
Classifier: Environment :: Console
Classifier: Intended Audience :: Developers
Classifier: License :: OSI Approved :: MIT License
Classifier: Operating System :: OS Independent
Classifier: Programming Language :: Python :: 3
Classifier: Programming Language :: Python :: 3 :: Only
Classifier: Topic :: Software Development
Classifier: Topic :: Software Development :: Quality Assurance
Classifier: Topic :: Software Development :: Testing
Requires-Dist: PyYAML
Requires-Dist: rich
Requires-Dist: regex ; extra == "regex"
Requires-Dist: pytest ; extra == "test"
Requires-Dist: pytest-cov ; extra == "test"
Requires-Dist: pytest-mock ; extra == "test"
Project-URL: Changelog, https://github.com/codingjoe/relint/releases
Project-URL: Project-URL, https://github.com/codingjoe/relint
Provides-Extra: regex
Provides-Extra: test
